{"scenario":{"battle.ks":{"まおうが　あらわれた！":"–It’s the demon lord!","まおう「はっはっは！":"Demon Lord: “Aaahahahaha!”","「ばかめっ！":"“You dolt!”","「そんな　ひんじゃくな　からだでは":"“There’s no way that you can defeat","「おれさまを　たおす　ことなど":"big, strong, *me*","「ぜったいに　ふかのう！":"with such a puny body!”","「その　からだには　もう":"“There’s not even any magic left","「まりょくも　ろくに　のこって　ないだろう？　":"in that pathetic little frame!”","「さっさと　あきらめて…":"“Just give up already…","「おれさまに　こうさんしろ！":"Surrender!”","こうさんしますか？":"--Will you surrender?--","はい":"Yes","いいえ":"No","・・・５ふんまえ":"…five minutes earlier…","ゆうしゃ「はあ　はあ　！":"Hero: *pant* *gasp*","「おい！":"“Hey!”","「なにを　モタモタ　してるんだ！":"“What are you *waiting* for?”","「はやく　サイコジャックの　まほうで":"“Hurry up and cast 「Psycho-Jack」– ","「まおうの　せいしんを　のっとって":"–it’ll let you take over the Demon Lord’s mind","「まおうを　あやつって　くれよ！":"and control his movements!”","「おい！きいてるのか！":"“Oi! Are you even listening?”","「もしかして　もう　まおうに　のりうつって":"“…Er, have you already gone and","「あやつってるのか？":"taken control of the Demon Lord?","「どっちなんだ…":"Ah jeez, did you or didn’t you…”","「くそ！　こうなったら　しかたがねえ！":"“Dammit, looks like there’s nothing for it but…","「おれさま　ひとりで　まおうをたおすぞ！":"I’ll take the demon king down by myself!","「レベル１ゆうしゃの　おくのてだ！":"I’ll use my level to my advantage…”","「はっはっは！":"“Aaahahahaha!”","「そうか　そうか":"“I see… I’m surprised…”","「だがな…":"“But I must admit…","「あきらめたら　そこで！":"I’m a bit disappointed that it’s already over…","「しあい　しゅうりょう　だ！":"Oh well, let’s finish it!”","まおうの　こうげき！":"The Demon Lord attacks!","ゆうしゃは　９９９９のダメージをうけた！":"The Hero receives 9999 damage!","ゆうしゃは　しんでしまった。":"The Hero has fallen…","「くっ！":"“Tch!","「おろかなやつめ！":"You’re so dumb!”","「おもいしらせてやる！":"“I guess I’ll just have to teach you!”","まおうは　おどろいている！":"The Demon Lord is startled!","まおう「き、きさま…":"Demon Lord: “Hey, no fair!”","「ひきょうだぞ！":"“You jerk!","「まだ　はなしの　とちゅう　じゃないか！":"I was still talking!”","「きたない　やつめ！　":"“Dirty cheater!","「おもいしらせて　やる！":"I’ll teach you proper manners. Pay attention!”","ゆうしゃの　こうげき！":"The Hero attacks!","まおうに　０のダメージ！":"The Demon Lord receives 0 damage!","まおうに　ダメージを　あたえられない！":"You can’t hurt the Demon Lord!","「やい　まおう！":"“Hey, Demon Lord!","「いまから　おれさまが　チェンジのまほうで":"I’ll cast 「Change」 and steal your body,","「おまえの　からだを　うばってやる！":"how do you like the sound of that?”","「かくごしろ！":"“Here it comes!”","「もしかして　もう":"“…Er, have you already gone and","「まおうを　あやつってるのか？":"taken control of the Demon Lord?","「くそ！":"“Dammit, looks like there’s nothing for it but…","「…しかたがねえ！":"I’ll take the demon king down by myself!","「こうなったら　おくのてだ！":"I’ll use my level to my advantage…”","「おまえの　からだを　うばってやるぞ！":"how do you like the sound of that?”","まおう（１ぴき）":"Demon Lord (single-target)","ゆうしゃは　にげだした！":"The Hero fled!","しかし　まおうからは　にげられない！":"–But you can't escape the Demon Lord!","ゆうしゃは　チェンジ　をとなえた！":"The Hero cast 「Change」!","ゆうしゃと　まおうのからだが　いれかわった！":"The Hero and the Demon Lord exchanged bodies!","ゆうしゃは　ホーリーを　となえた！":"The Hero cast 「Holy」!","まおうに　９９９９のダメージ！":"The Demon Lord received 9999 damage!","まおうをたおした！":"The Demon Lord was defeated!","ゆうしゃ（１り）":"Hero (single-target)","ゆうしゃに　９９９９のダメージ！！":"The Hero received 9999 damage!","まおうは　にげない！":"The Demon Lord can’t flee!"},"end.ks":{"どこから　ともなく　ししょうの　こえが":"You heard the voice of your old master","きこえてくる…":"faintly echoing once again…","「こまった　ときは":"“When yeh find yerself in a heap o’ trouble,","「たたかいのおうぎのしょを　よむ　のじゃ！":"try referrin’ to 「The Basics of Brawling」!”","「まおうを　たおすには":"“T’beat th’ Demon Lord","「まおうの　どうぐが":"yer gonna need t’use…","「ぜったいに　ひつよう　なのじゃ！":"his own tools against ’im!”","「じゅもんを　つかうには":"“T’cast a spell, y’need MP!","「エーテルで　ＭＰをかいふく　するのじゃ！":"Use a damn 「Ether」!”","「ゆうしゃの　たましいが":"“If the Hero’s spirit","「ゆうしゃの　からだの　なかに　なければ":"is not in the Hero’s body,","「ホーリーの　じゅもんは　つかえんぞ！":"You can’t cast 「Holy」!”","「じぶんが　いったい　だれ　なのか":"“Think one more time about","「もういちど　よく　かんがえるのじゃ":"just *who* y’really are!”","「まおうの　からだを　たおさねば":"“If yeh haven’t defeated th’ Demon Lord’s body,","「まおうを　たおした　ことには　ならぬぞ！":"yeh haven’t defeated th’ Demon Lord!”","ゆうしゃ「やった！　まおうを　たおしたぞ！":"Hero: “Yeah! We got him! We beat the Demon Lord!”","「おい！":"“Hey!”","「かくれてないで　でてこい！":"“You can stop hiding now, come on out!”","ゆうしゃ「おつかれ！":"Hero: “Great job back there!”","「おまえ　ちゃんと　サイコジャックの　まほうで":"“That was so cool! Your「Psycho Jack」spell","「まおうのせいしんを　あやつって　くれてたんだな":"let you take complete control of the Demon Lord!","「たすかったぜ！":"You *really* saved my bacon!”","「え？　おれさまが":"“Huh? ","「チェンジの　まほうを　つかったから":"My「Change」spell made things","「ややこしく　なった？":"all complicated and confusing?”","「まあ　いいじゃねえか！":"“Meh, whatever! It all turned out fine!","「まおうは　たおせたんだからよ！":"We actually beat the Demon Lord!”","「おまえの":"“That spell of yours is really something.","「てきの　せいしんをのっとる　まほうが　あれば":"Controlling your enemy’s mind…","「まおう　だって　こわくないぜ！":"Even a Demon Lord is nothing to fear!”","「これからも　よろしくな！":"“I’ll be counting on you even more from now on!","「はっはっは！":"Aaahahahaha!”"},"first.ks":{"たたかいのおうぎしょ":"「The Basics of Brawling」","ゆうしゃ":"Hero","LV":"LV","HP":"HP","MP":"MP","まおう":"Demon Lord","たたかう":"Attack","にげる":"Flee","じゅもん":"Magic","どうぐ":"Tools","ファイラ(MP30)":"Fire (30MP)","ブリザド(MP30)":"Blizzard (30MP)","チェンジ(MP30)":"Change (30MP)","ホーリー(MP100)":"Holy (100MP)","ヘルファイア（MP50）":"Hellfire (50MP)","アイスビーム（MP50）":"Ice Beam (50MP)","タイムリープ（MP100）":"Time Leap (100MP)","ゆうしゃのにっき":"「Hero’s Journal」","ししょうのてがみ":"「The Master’s Letter」","げっかんまほうガイド":"「Teen Mage Spell Guide」","やくそう":"「Medicine」","エーテル":"「Ether」","まおうのにっき":"「Demon Lord’s Letter」","４てんのうのてがみ":"「Four Kings’ Letter」","だいまおうのこころえ":"「The Three Tenets」"},"magic.ks":{"MPが足りない":"Not enough MP.","まおう（１ぴき）":"Demon Lord (single-target)","ゆうしゃは　ファイア　をとなえた！":"The Hero cast 「Fire」!","まおうに　０のダメージ！":"The Demon Lord receives 0 damage!","まおうに　ダメージを　あたえられない！":"You can’t hurt the Demon Lord!","ゆうしゃは　ブリザド　をとなえた！":"The Hero cast 「Blizzard」!","ゆうしゃは　チェンジ　をとなえた！":"The Hero cast 「Change」!","ゆうしゃと　まおうのからだが　いれかわった！":"The Hero and the Demon Lord exchanged bodies!","ゆうしゃは　ホーリー　をとなえた！":"The Hero cast 「Holy」!","だが　このじゅもんは　しんのゆうしゃ　にしか":"But only a True Hero can use this spell!","つかえない！":"It fizzles…","ゆうしゃ（１り）":"Hero (single-target)","まおうは　ヘルファイア　をとなえた！":"The Demon Lord cast 「Hellfire」!","ゆうしゃに　９９９９のダメージ！":"The Hero receives 9999 damage!","ゆうしゃは　しんでしまった":"The Hero has fallen…","まおうは　アイスビーム　をとなえた！":"The Demon Lord cast 「Ice Beam」!","まおうは　タイムリープ　をとなえた！":"The Demon Lord cast 「Time Leap」!","まおうの　せいしんが　じかんを　かこへ　":"The Demon Lord’s consciousness","さかのぼる！":"Leaps into the past!"},"opening.ks":{"あなたの　なまえを　にゅうりょく　してください":"Please enter your name:","とうろく":"Accept","あなたの　なまえは":"Your name is","「":" “","」":"” ","です。よろしいですか？":"Is that right?","はい":"Yes","いいえ":"No","その　なまえは　つかえません！":"You can’t use that name. Try again.","その　なまえは　つかえません":"You can’t use that name. Try again.","どこから　ともなく　ししょうの　こえが":"You hear the voice of your old master","きこえてくる…":"faintly echoing from some unknown place…","「おまえが　じぶんの　やくわりに　きがつけば":" “Once y’understand the role yer playin’,","「まおうを　たおす　ことなど　かんたんじゃ！":" defeatin’ the Demon Lord will be a piece o’ cake.","「ええか？":" Yeh got that?  Now go get ‘im!","「がんばるの　じゃぞ！":" The only one who can stop the Demon Lord","「まおうは　しんの　ゆうしゃにしか　たおせん！":" is a ‘True Hero,’ y’hear?","「おまえたちの　ちからを　あわせるのじゃ…":" It’ll take the both of yer powers combined…","「うう…":" …Ain’t that a worryin’ thought…”","わかったな？":"--Yeh got that?--"},"preload.ks":{"読み込み開始":"Loading the Game","１０％読み込み完了":"10%","２０％読み込み完了":"20%","３０％読み込み完了":"30%","４０％読み込み完了":"40%","５０％読み込み完了":"50%","６０％読み込み完了":"60%","７０％読み込み完了":"70%","８０％読み込み完了":"80%","９０％読み込み完了":"90%","１００％読み込み完了":"Loading Complete","ゲーム起動開始":"Launching…"},"staff.ks":{"クリアまでの回数":"Attempts until game clear:"},"title.ks":{"ゲームスタート":"Start the Game","はじめから":"From the beginning…","ゲームのせつめい":"Game Help","おとをならす":"Toggle sound on","おとをとめる":"Toggle sound off","りとらい":"Retry"},"tool.ks":{"ゆうしゃは　たたかいのおうぎのしょを　よんだ！":"The Hero read 「The Basics of Brawling」.","「たたかいのおうぎ":"“The Basics of Brawlin’…","「それは…":"If yeh only remember one thing, make it this:”","「せんてひっしょう！":"“Strike first and strike true!","「てきの　ふいをついて　こうげきすれば":"If yeh can strike the enemy while’e’s gettin’ ready,”","「てきよりも　１かい　おおく　こうどうできる！":"“yer strike will cut deeper than his.”","「てきが　しゃべっている　すきをついて":"“When your enemy is chattin’,","「いきなり　こうげき　するべし！":"that’s yer chance t’strike with all yer might!”","「ししょうより":"--Your beloved teacher.","ゆうしゃは　エーテル　をつかった！":"The Hero used an 「Ether」!","ゆうしゃの　ＭＰが　５０かいふくした！":"The Hero recovered 50 MP!","「ゆうしゃよ…":"“Hero…","「おまえは　ＭＰがあれば　あるぶんだけ":"If y’got just a bit o’ MP, and y’blow it all","「いちばん つよいじゅもんを　つかう　くせがある":"on the biggest spell y’can muster…”","「こまったものじゃ…":"“y’just get into more trouble…”","「ししょう　より":"--Your beloved teacher.","ゆうしゃは　げっかんまほうガイド　を　よんだ！":"The Hero read the「Teen Mage」Spell Guide Special Issue!","「こんげつの　まほう　かいせつ！":"This month’s hot spells for cool kids!","「ファイア…ほのおのまほう(ＭＰ３０)":"・Fire – Great for starting campfires, just don’t stand too close! (30MP)","「ブリザド…こおりのまほう(ＭＰ３０)":"・Blizzard – Try this on bananas for a quick and easy frozen treat! (30MP)","「チェンジ…からだをこうかん(ＭＰ３０)":"・Change – Trade bodies and see what it’s like in someone else’s shoes! (30MP)","「ヘルファイア…じごくのほのお(ＭＰ５０)":"・Hellfire – Never use unsupervised, you could burn down your house! (50MP)","「アイスビーム…ぜったいれいど(ＭＰ５０)":"・Ice Beam – Don’t let any fingers (or toes) get caught in the blast, they might freeze off! (50MP)","「タイムリープ…じかんいどう(ＭＰ１００)":"・Time Leap – Jump into the past and surprise your friends! (100MP)","「サイコジャック…あいてをあやつる(ＭＰ１００)":"・Psycho Jack – Put a stop to bullies by controlling their minds! (100MP)","「ホーリー…ひかりのまほう(ＭＰ１００)":"・Holy – Purify even the darkest of Demon Lords (may require some cleanup afterwards). (100MP)","ゆうしゃ":"Hero","まおう（１ぴき）":"Demon Lord (single-target)","ゆうしゃは　やくそう　をつかった！":"The Hero used 「Medicine」!","ゆうしゃの　ＨＰが　５０かいふくした！":"The Hero recovered 50 HP!","まおうの　ＨＰは　これいじょう　かいふくできない":"The Demon Lord is already at maximum HP.","まおうの　ＭＰが　５０かいふくした！":"The Demon Lord recovered 50 MP!","ゆうしゃは　ゆうしゃのにっきを　よんだ！":"The Hero read 「The Hero’s Journal」!","「わっはっはっは！":"“Waaahahahaha!!!","「おれさまは　ゆうしゃ　さまだ！":"It’s me! I’m the legendary Hero!”","「まおうは　おれさまにしか　たおせない！":"“I’m the only one who can beat the Demon Lord!","「だが　しゅぎょうなんて　かったるいことは":"But man, this apprenticeship, so much training…","「したくない！":"Forget it!”","「だから　レベル１のまま":"“Me and my buddy are just gonna head over","「なかまと　ふたりで":"to his castle and get it over with!","「まおうじょうに　なぐりこみだ！":"We’re still level 1, but…”","「まあ　なんとか　なるだろ":"“…Meh, it’ll work out somehow!”","「ゆうしゃ":"--Hero","ゆうしゃは　ししょうのてがみを　よんだ！":"The Hero read「The Master’s Letter」!","まおう":"Demon Lord","ゆうしゃ（１り）":"Hero (single-target)","まおうは　やくそう　をつかった！":"The Demon Lord used 「Medicine」!","まおうは　エーテル　をつかった！":"The Demon Lord used an 「Ether」!","「わしの　じゃくてんは":"“My only weakness","「ひかりの　まほう　じゃ":"is to the magic of light.”","「ひかりの　まほうは":"“It would appear that this magic","「ゆうしゃの　たましいと　からだを　もつものしか":"can only be used by he who possesses","「つかえんらしい！":"both the body and mind of a hero!”","「ゆうしゃたちは　そのことを　まだ　しらぬ":"“The Hero and his friends know this not.","「だから　ぜったいに　ひみつに　しておくのじゃ":"Therefore I must not allow them to learn of it!”","「まおう":"--The Demon Lord","「まおうさま…　もうしわけ　ありません！":"“Our deepest apologies, O great Demon Lord!","「われら　４てんのうは　まけました！":"We, the Four Heavenly Kings, have been defeated.”","「ゆうしゃは　ただの　ばかです":"“As you’ve likely noticed, The Hero is an utter fool…”","「しかし　なかまの":"“But you may not have realized that his friend,","という まほうつかいが":"is a great wizard –”","「サイコジャックの　まほうを　つかいます":"“able to cast even the mighty「Psycho Jack!」”","「やつは　われわれの　せいしんを":"“He was able to take control of our very will,","「のっとり　あやつります":"and control us as though we were simple puppets.”","「たとえ　まおうさま　でも":"“If he were to manage to control you, O Lord,","「あやつられて　しまったら　ばんじ　きゅうす！":"it would be an unimaginable disaster!”","「おきをつけください！…ぐふ":"“Please, be careful… May you fare better than we…”","「４てんのうより":"--The Four Heavenly Kings","「P.S":"“P.S.:","「まおうさまが　このてがみを　よむとき":"We sincerely hope that you aren’t already","「すでに　あやつられて　いませんように…":"being controlled as you read this message…”","まおうは　だいまおうのこころえ　を　よんだ！":"The Demon Lord read 「The Three Tenets」!","「だいまおうに　なるための　３つのこと":"“There are three tenets a Great Demon Lord must follow:”","「１．だいまおうは　にげない":"“・1. A Great Demon Lord never flees.","「まおうが　にげる　のは　":"Running from a fight is not befitting of one","「かっこわるい　ので　やめましょう":"so strong and noble, thus we shall not do it.”","「２．だいまおうは　てきに　しおを　おくらない":"“・2. A Great Demon Lord gives no quarter.","「どうぐを　あいてに　つかえる　からといって":"We shall not use any tools on our opponents’ behalf;","「てきを　かいふく　させては　いけません":"helping them to recover HP or MP is out of the question.”","「３．だいまおうは　ＭＰを　きらさない":"“・3. A Great Demon Lord does not run out of MP.","「いざというとき　まほうが　つかえないと":"Being unable to cast spells","「まおうの　いげんに　かかわります":"is an unconscionable indignity.”","「なので　たたかい　には　かならず":"“To prevent such an unthinkable occurrence,","「よびの　エーテルを　２つ　もっていきましょう":"we shall never begin a fight without *two* Ethers.”"},"tutorial.ks":{"「このゲームは":"“Yer now playin’ what I’ve been told is an…","「ＲＰＧ風コマンドバトル型謎解きゲーム　じゃ！":"「RPG-Style Command-Battle Puzzle-Solving Game」!” ","「なんじゃ　それ…？":"“~What the heck is that?~","「と　おもうのも　むりは　ない":"–is a thing that y'may be thinkin'.","「わしも　はじめて　きく　ジャンルじゃ":"Yeah, I’ve never heard o’ such a thing either.”","「じゃが　しんぱい　は　むよう":"“But let’s not worry about that! As I always say:","「やることは　たんじゅん！":"there’s nothin’ for it but t’do it!”","「まおうを　たおす！":"“Defeat the Demon King!","「ただ　それだけの　ミニゲーム":"I’m sure that such a simple goal will be no problem","「わかりやすい　じゃろ？":"for someone as practiced as you, right?”","「ただし　ゆうしゃの　レベルは１！":"“There’s just one twist: Yer hero is level 1!","「しゅぎょうも　ぼうけんも　なし":"There’s no adventure. No levelin’ up.","「いきなり　ラスボスと　たたかうのじゃ！":"It’s just straight to the last boss!”","「だいじょうぶ":"“Don’t worry!","「どうしても　こまったら　":"If y’get into serious trouble,","「わしが　アドバイスを　してやるぞ！":"I’ll give yeh some tips.”","「え？":"“Hmm? What’s that?","「いま　しゃべっとる　わしは　だれなのかって？":"Who’m I?”","「ばかもん！":"“Stop goofin’ around!","「わしは　おまえたちの　ししょう　じゃ！":"It’s me, yer beloved teacher.","「そんけい　するのじゃ！":"Whom yeh *respect* very much – isn’t that right?”","「がんばるのじゃぞ！":"“Now get out there and fight!”"}},"tag":{"glink":"text","ptext":"text"},"chara":{},"label":{}}